lovage/__init__.py
lovage/backends/__init__.py
lovage/backends/awslambda/__init__.py
lovage/backends/awslambda/cf.py
lovage/backends/awslambda/helpers/deleter.py
lovage/backends/awslambda/helpers/packager.py
lovage/backends/base.py
lovage/backends/local.py
lovage/dirtools.py
lovage/exceptions.py
lovage/utils.py
lovage-0.0.7.dist-info/LICENSE
lovage-0.0.7.dist-info/WHEEL
lovage-0.0.7.dist-info/METADATA
lovage-0.0.7.dist-info/RECORD
