Metadata-Version: 2.1
Name: lovage
Version: 0.0.7
Summary: Kind of like Celery, but simpler and with more Lambda
Home-page: https://github.com/CloudSnorkel/lovage
License: MIT
Keywords: celery,queue,task,lambda,serverless
Author: CloudSnorkel
Author-email: amir@cloudsnorkel.com
Requires-Python: >=3.6,<4.0
Classifier: Development Status :: 3 - Alpha
Classifier: Intended Audience :: Developers
Classifier: License :: OSI Approved :: MIT License
Classifier: Programming Language :: Python
Classifier: Programming Language :: Python :: 3
Classifier: Programming Language :: Python :: 3.6
Classifier: Programming Language :: Python :: 3.7
Classifier: Programming Language :: Python :: 3.8
Classifier: Programming Language :: Python :: 3.9
Classifier: Topic :: Software Development :: Libraries :: Application Frameworks
Requires-Dist: boto3 (>=1.17.38,<2.0.0)
Requires-Dist: globster (==0.1.0)
Requires-Dist: troposphere (>=2.7.0,<3.0.0)
Project-URL: Repository, https://github.com/CloudSnorkel/lovage
